twitter_api/__init__.py
twitter_api/client/__init__.py
twitter_api/client/oauth_flow/__init__.py
twitter_api/client/oauth_flow/twitter_oauth1_access_token_client.py
twitter_api/client/oauth_flow/twitter_oauth1_access_token_mock_client.py
twitter_api/client/oauth_flow/twitter_oauth1_access_token_real_client.py
twitter_api/client/oauth_flow/twitter_oauth1_authorization_client.py
twitter_api/client/oauth_flow/twitter_oauth1_authorization_mock_client.py
twitter_api/client/oauth_flow/twitter_oauth1_request_token_client.py
twitter_api/client/oauth_flow/twitter_oauth1_request_token_mock_client.py
twitter_api/client/oauth_flow/twitter_oauth1_request_token_real_client.py
twitter_api/client/oauth_flow/twitter_oauth2_access_token_client.py
twitter_api/client/oauth_flow/twitter_oauth2_access_token_mock_client.py
twitter_api/client/oauth_flow/twitter_oauth2_access_token_real_client.py
twitter_api/client/oauth_flow/twitter_oauth2_authorization_client.py
twitter_api/client/oauth_flow/twitter_oauth2_authorization_mock_client.py
twitter_api/client/oauth_flow/twitter_oauth2_authorization_real_client.py
twitter_api/client/oauth_session/__init__.py
twitter_api/client/oauth_session/resources/__init__.py
twitter_api/client/oauth_session/resources/oauth1_access_token/__init__.py
twitter_api/client/oauth_session/resources/oauth1_access_token/post_oauth1_access_token.py
twitter_api/client/oauth_session/resources/oauth1_authenticate/__init__.py
twitter_api/client/oauth_session/resources/oauth1_authenticate/generate_authorization_url_oauth1_authenticate.py
twitter_api/client/oauth_session/resources/oauth1_authorize/__init__.py
twitter_api/client/oauth_session/resources/oauth1_authorize/generate_authorization_url_oauth1_authorize.py
twitter_api/client/oauth_session/resources/oauth1_request_token/__init__.py
twitter_api/client/oauth_session/resources/oauth1_request_token/post_oauth1_request_token.py
twitter_api/client/oauth_session/resources/oauth2_authorize/__init__.py
twitter_api_py-0.9.0.dist-info/LICENSE
twitter_api_py-0.9.0.dist-info/METADATA
twitter_api_py-0.9.0.dist-info/WHEEL
twitter_api_py-0.9.0.dist-info/RECORD
