Metadata-Version: 2.1
Name: twitter-api-py
Version: 0.9.0
Summary: Twitter API Client by Typed Python.
Home-page: https://github.com/yassun4dev/twitter-api-py
License: BSD-3-Clause
Author: yassun4dev
Author-email: yassun4dev@outlook.com
Requires-Python: >=3.9,<4.0
Classifier: Development Status :: 4 - Beta
Classifier: Intended Audience :: Developers
Classifier: License :: OSI Approved :: BSD License
Classifier: Programming Language :: Python :: 3
Classifier: Programming Language :: Python :: 3.9
Classifier: Programming Language :: Python :: 3.10
Classifier: Programming Language :: Python :: 3.11
Classifier: Programming Language :: Python :: 3 :: Only
Classifier: Topic :: Software Development :: Libraries
Requires-Dist: authlib (>=1.2.0,<2.0.0)
Requires-Dist: httpx (>=0.24.0,<0.25.0)
Requires-Dist: pydantic (>=1.10.7,<2.0.0)
Requires-Dist: typing-extensions (>=4.5.0,<5.0.0)
Project-URL: Repository, https://github.com/yassun4dev/twitter-api-py
